mstp/__init__.py
mstp/dh/__init__.py
mstp/secure/__init__.py
mstp/simple/__init__.py
mstp-0.2.0.dist-info/LICENSE
mstp-0.2.0.dist-info/METADATA
mstp-0.2.0.dist-info/WHEEL
mstp-0.2.0.dist-info/top_level.txt
mstp-0.2.0.dist-info/RECORD
