Metadata-Version: 2.1
Name: mstp
Version: 0.2.0
Summary: secure data transfer protocol
Home-page: UNKNOWN
Author: m5k
Author-email: spam@m5k.ru
License: UNKNOWN
Platform: UNKNOWN
Classifier: Programming Language :: Python :: 3.8
Classifier: License :: OSI Approved :: MIT License
Classifier: Operating System :: OS Independent
Requires-Python: >=3.6
License-File: LICENSE
Requires-Dist: cryptography (<=3.4.8)
